cyrating/__init__.py
cyrating/api.py
cyrating-1.0.18.dist-info/LICENSE
cyrating-1.0.18.dist-info/METADATA
cyrating-1.0.18.dist-info/WHEEL
cyrating-1.0.18.dist-info/RECORD
