Metadata-Version: 2.1
Name: cyrating
Version: 1.0.18
Summary: Python wrapper for https://www.cyrating.com
Home-page: https://www.cyrating.com
License: ISC
Keywords: cyrating
Author: Cyrating
Author-email: tech@cyrating.com
Requires-Python: >=3.6,<4.0
Classifier: License :: OSI Approved
Classifier: Programming Language :: Python :: 3
Classifier: Programming Language :: Python :: 3.6
Classifier: Programming Language :: Python :: 3.7
Classifier: Programming Language :: Python :: 3.8
Classifier: Programming Language :: Python :: 3.9
Classifier: Programming Language :: Python :: 3.10
Classifier: Programming Language :: Python :: 3.11
Classifier: Programming Language :: Python :: 3.12
Classifier: Topic :: Security
Requires-Dist: PyJWT (>=2.1.0,<3.0.0)
Requires-Dist: configparser (>=5.0.2,<6.0.0)
Requires-Dist: requests (>=2.25.1,<3.0.0)
